tairHaystack/__init__.py
tairHaystack/document_stores/__init__.py
tairHaystack/document_stores/errors.py
tairHaystack/document_stores/filter_utils.py
tairHaystack/document_stores/tairvector.py
tairHaystack-1.0.0.dist-info/METADATA
tairHaystack-1.0.0.dist-info/WHEEL
tairHaystack-1.0.0.dist-info/top_level.txt
tairHaystack-1.0.0.dist-info/RECORD
