Metadata-Version: 2.1
Name: tairHaystack
Version: 1.0.0
Summary: Tair vector database with Haystack
Author: Zhidong Tan
Author-email: <2741986499@email.com>
Keywords: tair,haystack
Classifier: Development Status :: 3 - Alpha
Classifier: Intended Audience :: Developers
Classifier: Programming Language :: Python :: 2
Classifier: Programming Language :: Python :: 3
Classifier: Operating System :: MacOS :: MacOS X
Classifier: Operating System :: Microsoft :: Windows
Requires-Dist: haystack
Requires-Dist: tair
